data_monitor_drm/__init__.py
data_monitor_drm/app.py
data_monitor_drm/cli.py
data_monitor_drm-0.1.0.dist-info/METADATA
data_monitor_drm-0.1.0.dist-info/WHEEL
data_monitor_drm-0.1.0.dist-info/entry_points.txt
data_monitor_drm-0.1.0.dist-info/top_level.txt
data_monitor_drm-0.1.0.dist-info/RECORD
