Metadata-Version: 2.4
Name: data-monitor-drm
Version: 0.1.0
Summary: Dash-based job monitor with collapsible Live/Backfill table + clickable KPIs/pies
Author-email: Your Name <you@example.com>
License-Expression: MIT
Requires-Python: >=3.9
Requires-Dist: dash<3,>=2.11
Requires-Dist: dash-bootstrap-components<2,>=1.5
Requires-Dist: Flask<3.1,>=2.2
Requires-Dist: pytz
